fortune_cookie/__init__.py
fortune_cookie/app.py
fortune_cookie_factory-0.0.2.dist-info/entry_points.txt
fortune_cookie_factory-0.0.2.dist-info/METADATA
fortune_cookie_factory-0.0.2.dist-info/WHEEL
fortune_cookie_factory-0.0.2.dist-info/RECORD
