Metadata-Version: 2.1
Name: fortune-cookie-factory
Version: 0.0.2
Summary: 
Author: yuyatinnefeld
Author-email: yuyatinnefeld@gmail.com
Requires-Python: >=3.7,<4.0
Classifier: Programming Language :: Python :: 3
Classifier: Programming Language :: Python :: 3.7
Classifier: Programming Language :: Python :: 3.8
Classifier: Programming Language :: Python :: 3.9
Classifier: Programming Language :: Python :: 3.10
Classifier: Programming Language :: Python :: 3.11
